{
    "data": {
        "animals": [
            {
                "id": "1",
                "species": "Cachorro",
                "name": "Bolinha",
                "date": "17/04/2019",
                "category": "Encontrado",
                "size": "Pequeno",
                "city": "São Paulo",
                "gender": "Macho",
                "details": "Esse lindo gatinho foi encontrado na rua",
                "image": "https://www.ocregister.com/wp-content/uploads/2019/04/0428-REAL-HOAHOMEFRONT-DOGS-1.jpg?w=523"
            },
            {
                "id": "2",
                "species": "Cachorro",
                "name": "Biscoito",
                "date": "17/03/2019",
                "category": "Encontrado",
                "size": "Grande",
                "city": "Guarulhos",
                "gender": "Macho",
                "details": "Esse lindo cachorrinho foi encontrado na rua",
                "image": "https://www.guidedogs.org/wp-content/uploads/2018/01/Mobile.jpg"
            },
            {
                "id": "3",
                "species": "Cachorro",
                "name": "Bu",
                "date": "25/03/2019",
                "category": "Encontrado",
                "size": "Pequeno",
                "city": "São Bernando do Campo",
                "gender": "Fêmea",
                "details": "Esse lindo coelhinho foi encontrado na rua",
                "image": "https://vets-now.s3.amazonaws.com/uploads/2017/01/Dog-laboured-breathing-Vets-Now.jpg"
            },
            {
                "id": "4",
                "species": "Cachorro",
                "name": "Julieta",
                "date": "09/05/2019",
                "category": "Encontrado",
                "size": "Pequeno",
                "city": "Santo André",
                "gender": "Fêmea",
                "details": "Esse lindo porquinho da India foi encontrado na rua",
                "image": "https://s3.amazonaws.com/cdn-origin-etr.akc.org/wp-content/uploads/2017/11/13002253/GettyImages-521536928-_1_.jpg"
            },
            {
                "id": "5",
                "species": "Cachorro",
                "name": "Robson",
                "date": "21/04/2019",
                "category": "Encontrado",
                "size": "Pequeno",
                "city": "Mauá",
                "gender": "Macho",
                "details": "Esse lindo gatinho foi encontrado na rua",
                "image": "https://wtop.com/wp-content/uploads/2019/07/Daisy_3-1481x1254.jpeg"
            },
            {
                "id": "6",
                "species": "Cachorro",
                "name": "Robson",
                "date": "15/06/2019",
                "category": "Encontrado",
                "size": "Pequeno",
                "city": "São Paulo",
                "gender": "Macho",
                "details": "Esse lindo gatinho foi encontrado na rua",
                "image": "https://i2.wp.com/metro.co.uk/wp-content/uploads/2018/04/sei_7959691.jpg?quality=90&strip=all&zoom=1&resize=644%2C853&ssl=1"
            },
            {
                "id": "7",
                "species": "Cachorro",
                "name": "Robson",
                "date": "06/07/2019",
                "category": "Encontrado",
                "size": "Pequeno",
                "city": "São Paulo",
                "gender": "Macho",
                "details": "Esse lindo gatinho foi encontrado na rua",
                "image": "https://khn.org/wp-content/uploads/sites/2/2019/06/HighDogs1.jpg"
            },
            {
                "id": "8",
                "species": "Cachorro",
                "name": "Robson",
                "date": "12/04/2019",
                "category": "Encontrado",
                "size": "Pequeno",
                "city": "São Caetano",
                "gender": "Macho",
                "details": "Esse lindo gatinho foi encontrado na rua",
                "image": "https://g77v3827gg2notadhhw9pew7-wpengine.netdna-ssl.com/wp-content/uploads/2018/11/DogFt11-1024x682.jpg"
            }
        ]
    }
}